{
  "camera": {
    "width": 640,
    "height": 480,
    "pixel_format": "RGB888",
    "focus": "continuous",
    "lens_position": 2.0
  },
  "hsv": {
    "lower": [68, 180, 20],
    "upper": [88, 255, 255]
  },
  "morphology": {
    "kernel_size": 5,
    "open_iterations": 1,
    "close_iterations": 2
  },
  "tracker": {
    "min_area": 300.0,
    "min_circularity": 0.55,
    "smoothing_alpha": 0.35
  },
  "scoring": {
    "min_score": 0.55,
    "color_fill_enabled": true,
    "color_fill_weight": 0.25,
    "circularity_enabled": true,
    "circularity_weight": 0.05,
    "circle_fit_enabled": true,
    "circle_fit_weight": 0.25,
    "enclosing_fill_enabled": true,
    "enclosing_fill_weight": 0.15,
    "solidity_enabled": true,
    "solidity_weight": 0.1,
    "relative_area_enabled": true,
    "relative_area_weight": 0.2,
    "shading_enabled": false,
    "shading_weight": 0.05,
    "shading_min_area": 400.0
  }
}
